odoo/addons/website_sale_product_attribute_value_filter_existing/README.rst
odoo/addons/website_sale_product_attribute_value_filter_existing/__init__.py
odoo/addons/website_sale_product_attribute_value_filter_existing/__manifest__.py
odoo/addons/website_sale_product_attribute_value_filter_existing/controllers/__init__.py
odoo/addons/website_sale_product_attribute_value_filter_existing/controllers/main.py
odoo/addons/website_sale_product_attribute_value_filter_existing/i18n/ca.po
odoo/addons/website_sale_product_attribute_value_filter_existing/i18n/es.po
odoo/addons/website_sale_product_attribute_value_filter_existing/i18n/it.po
odoo/addons/website_sale_product_attribute_value_filter_existing/i18n/nl.po
odoo/addons/website_sale_product_attribute_value_filter_existing/i18n/pt_BR.po
odoo/addons/website_sale_product_attribute_value_filter_existing/i18n/tr.po
odoo/addons/website_sale_product_attribute_value_filter_existing/i18n/website_sale_product_attribute_value_filter_existing.pot
odoo/addons/website_sale_product_attribute_value_filter_existing/readme/CONFIGURATION.rst
odoo/addons/website_sale_product_attribute_value_filter_existing/readme/CONTRIBUTORS.md
odoo/addons/website_sale_product_attribute_value_filter_existing/readme/CREDITS.md
odoo/addons/website_sale_product_attribute_value_filter_existing/readme/DESCRIPTION.md
odoo/addons/website_sale_product_attribute_value_filter_existing/static/description/icon.png
odoo/addons/website_sale_product_attribute_value_filter_existing/static/description/index.html
odoo/addons/website_sale_product_attribute_value_filter_existing/static/src/js/website_sale_product_attribute_value_filter_existing_search_desk_tour.esm.js
odoo/addons/website_sale_product_attribute_value_filter_existing/static/src/js/website_sale_product_attribute_value_filter_existing_tour.esm.js
odoo/addons/website_sale_product_attribute_value_filter_existing/tests/__init__.py
odoo_addon_website_sale_product_attribute_value_filter_existing-18.0.1.1.0.2.dist-info/METADATA
odoo_addon_website_sale_product_attribute_value_filter_existing-18.0.1.1.0.2.dist-info/WHEEL
odoo_addon_website_sale_product_attribute_value_filter_existing-18.0.1.1.0.2.dist-info/top_level.txt
odoo_addon_website_sale_product_attribute_value_filter_existing-18.0.1.1.0.2.dist-info/RECORD
